<annotation>
	<folder></folder>
	<filename>army79_jpg.rf.f85ab1f22f423311d3ca069f94ce1840.jpg</filename>
	<path>army79_jpg.rf.f85ab1f22f423311d3ca069f94ce1840.jpg</path>
	<source>
		<database>roboflow.ai</database>
	</source>
	<size>
		<width>640</width>
		<height>640</height>
		<depth>3</depth>
	</size>
	<segmented>0</segmented>
	<object>
		<name>armyworm</name>
		<pose>Unspecified</pose>
		<truncated>0</truncated>
		<difficult>0</difficult>
		<occluded>0</occluded>
		<bndbox>
			<xmin>153</xmin>
			<xmax>494</xmax>
			<ymin>197</ymin>
			<ymax>411</ymax>
		</bndbox>
	</object>
</annotation>
