<annotation>
	<folder></folder>
	<filename>army139_jpg.rf.5208c8f3ca1c866c5910c98cdd022aa1.jpg</filename>
	<path>army139_jpg.rf.5208c8f3ca1c866c5910c98cdd022aa1.jpg</path>
	<source>
		<database>roboflow.ai</database>
	</source>
	<size>
		<width>640</width>
		<height>640</height>
		<depth>3</depth>
	</size>
	<segmented>0</segmented>
	<object>
		<name>armyworm</name>
		<pose>Unspecified</pose>
		<truncated>0</truncated>
		<difficult>0</difficult>
		<occluded>0</occluded>
		<bndbox>
			<xmin>288</xmin>
			<xmax>641</xmax>
			<ymin>208</ymin>
			<ymax>504</ymax>
		</bndbox>
	</object>
</annotation>
