<annotation>
	<folder></folder>
	<filename>army197_jpg.rf.801e3257518878facac0aa2ec14e1223.jpg</filename>
	<path>army197_jpg.rf.801e3257518878facac0aa2ec14e1223.jpg</path>
	<source>
		<database>roboflow.ai</database>
	</source>
	<size>
		<width>640</width>
		<height>640</height>
		<depth>3</depth>
	</size>
	<segmented>0</segmented>
	<object>
		<name>armyworm</name>
		<pose>Unspecified</pose>
		<truncated>0</truncated>
		<difficult>0</difficult>
		<occluded>0</occluded>
		<bndbox>
			<xmin>51</xmin>
			<xmax>375</xmax>
			<ymin>1</ymin>
			<ymax>257</ymax>
		</bndbox>
	</object>
</annotation>
