<annotation>
	<folder></folder>
	<filename>image-595-_jpg.rf.a9780d1894780701ae0ecf33ddd08efd.jpg</filename>
	<path>image-595-_jpg.rf.a9780d1894780701ae0ecf33ddd08efd.jpg</path>
	<source>
		<database>roboflow.com</database>
	</source>
	<size>
		<width>640</width>
		<height>640</height>
		<depth>3</depth>
	</size>
	<segmented>0</segmented>
	<object>
		<name>worm</name>
		<pose>Unspecified</pose>
		<truncated>0</truncated>
		<difficult>0</difficult>
		<occluded>0</occluded>
		<bndbox>
			<xmin>108</xmin>
			<xmax>486</xmax>
			<ymin>19</ymin>
			<ymax>571</ymax>
		</bndbox>
	</object>
	<metadata>
	</metadata>
</annotation>
