<annotation>
	<folder></folder>
	<filename>image-652-_jpg.rf.7e6917ddacb34cfa01b4e8ad39ca0b03.jpg</filename>
	<path>image-652-_jpg.rf.7e6917ddacb34cfa01b4e8ad39ca0b03.jpg</path>
	<source>
		<database>roboflow.com</database>
	</source>
	<size>
		<width>640</width>
		<height>640</height>
		<depth>3</depth>
	</size>
	<segmented>0</segmented>
	<object>
		<name>worm</name>
		<pose>Unspecified</pose>
		<truncated>0</truncated>
		<difficult>0</difficult>
		<occluded>0</occluded>
		<bndbox>
			<xmin>166</xmin>
			<xmax>541</xmax>
			<ymin>76</ymin>
			<ymax>587</ymax>
		</bndbox>
	</object>
	<object>
		<name>worm</name>
		<pose>Unspecified</pose>
		<truncated>0</truncated>
		<difficult>0</difficult>
		<occluded>0</occluded>
		<bndbox>
			<xmin>1</xmin>
			<xmax>641</xmax>
			<ymin>24</ymin>
			<ymax>640</ymax>
		</bndbox>
	</object>
	<metadata>
	</metadata>
</annotation>
