<annotation>
	<folder></folder>
	<filename>image-1241-_jpg.rf.2a5470595f894b777be40f42f508e174.jpg</filename>
	<path>image-1241-_jpg.rf.2a5470595f894b777be40f42f508e174.jpg</path>
	<source>
		<database>roboflow.com</database>
	</source>
	<size>
		<width>640</width>
		<height>640</height>
		<depth>3</depth>
	</size>
	<segmented>0</segmented>
	<object>
		<name>worm</name>
		<pose>Unspecified</pose>
		<truncated>0</truncated>
		<difficult>0</difficult>
		<occluded>0</occluded>
		<bndbox>
			<xmin>100</xmin>
			<xmax>601</xmax>
			<ymin>25</ymin>
			<ymax>508</ymax>
		</bndbox>
	</object>
	<metadata>
	</metadata>
</annotation>
